Workbook

Sheet Intraday or Delivery RM
B2: Intraday Calculator | C2: Dhan | L2: Initial Cap. | M2: 40000 | N2: Additional if added
E3: Type of Trade | F3: Intraday | I3: Start Date | J3: 45840 | L3: Total Cap. | M3: =M2+N3 -> 40000 | N3: 0
B4: Leverage | C4: =IF(F3="Intraday",5,1) -> 5 | I4: Today's Date | J4: =TODAY() -> 45991 | L4: Current | M4: =M3+M6 -> 46735.03
F5: Percent | G5: Amount
B6: Position to be used for desired SL TGT | C6: =G10/F13 -> 240572.82 | E6: Position | F6: 1 | G6: =C8 -> 209400 | I6: Total Money | J6: {=LOOKUP(2,1/(M12:M36>=0),M12:M15)} -> 46735.03 | L6: Returns | M6: =SUM(K12:K36) -> 6735.03
B7: Position amount we can have | C7: =J7 -> 233675.15 | E7: Leverage Funds | F7: =F6-F8 -> 0.8 | G7: =G6*F7 -> 167520 | I7: Total Position | J7: =J6*C4 -> 233675.15 | L7: Returns % | M7: =M6/M3 -> 0.16837575
B8: Position Used | C8: =C15*C16 -> 209400 | E8: Your Funds | F8: =1/C4 -> 0.2 | G8: =G6*F8 -> 41880 | L8: Check -------> | M8: =IF(M4=J6,"Sahi Hai Bhai!","Kuch toh gadbad hai Daya!") -> Sahi Hai Bhai!
B10: Rate of MTF | C10: 0 | E10: Risk | F10: 0.02 | G10: =J6*(F10) -> 934.7006 | I10: Daily Ledger
B11: Charge on Borrowed Amount | I11: Trade Day | J11: Amount | K11: PnL | L11: PnL % | M11: Balance | N11: Date
B12: Total Charge | C12: 0 | E12: Target | F12: =ABS(($C$15-(F21*$G$10+'Order Estimator'!$C$18)/$C$16)/$C$15-1) -> 0.0095058135 | G12: =IF(G15="B",C15*(1+F12),C15*(1-F12)) -> 605.70349 | I12: 1 | J12: =M3 -> 40000 | K12: 1599.31 | L12: =K12/J12 -> 0.03998275 | M12: =J12+K12 -> 41599.31 | N12: 45841
E13: Stop Loss | F13: =ABS(($C$15-($G$10-'Order Estimator'!$C$18)/$C$16)/$C$15-1) -> 0.0038853126 | G13: =IF(G15="B",C15*(1-F13),C15*(1+F13)) -> 597.66881 | I13: 2 | J13: =M12 -> 41599.31 | K13: -831.99 | L13: =K13/J13 -> -0.020000091 | M13: =J13+K13 -> 40767.32 | N13: 45842
B14: Stock | I14: 3 | J14: =M13 -> 40767.32 | K14: 1629.98 | L14: =K14/J14 -> 0.039982515 | M14: =J14+K14 -> 42397.3 | N14: 45845
B15: LTP | C15: 600 | E15: Order Type | F15: (Buy or Sell) | G15: b | I15: 4 | J15: =M14 -> 42397.3 | K15: -847.95 | L15: =K15/J15 -> -0.020000094 | M15: =J15+K15 -> 41549.35 | N15: 45846
B16: Quantity | C16: =ROUNDDOWN((C7*0.9)/C15,0) - 1 -> 349 | I16: 5 | J16: =M15 -> 41549.35 | K16: 1661.26 | L16: =K16/J16 -> 0.039982816 | M16: =J16+K16 -> 43210.61 | N16: 45847
I17: 6 | J17: =M16 -> 43210.61 | K17: 1727.67 | L17: =K17/J17 -> 0.039982541 | M17: =J17+K17 -> 44938.28 | N17: 45848
B18: Gross Profit | C18: =IF(G15="B",(G12-C15)*C16,(C15-G12)*C16) -> 1990.5173 | E18: Theoretical Risk:Reward | F18: =F12/F13 -> 2.446602 | I18: 7 | J18: =M17 -> 44938.28 | K18: 1796.75 | L18: =K18/J18 -> 0.039982616 | M18: =J18+K18 -> 46735.03 | N18: 45849
B19: Gross Loss | C19: =IF(G15="B",(G13-C15)*C16,(C15-G13)*C16) -> -813.58446 | E19: Practical Risk Reward | F19: =ABS(C20/C21) -> 1.999143 | I19: 8 | J19: =M18 -> 46735.03 | L19: =K19/J19 -> 0 | M19: =J19+K19 -> 46735.03
B20: Total Profit | C20: =IF(G15="B",C18-C11-'Order Estimator'!C17,-C11+C18-'Order Estimator'!C17) -> 1868.6001 | I20: 9 | J20: =M19 -> 46735.03 | L20: =K20/J20 -> 0 | M20: =J20+K20 -> 46735.03
B21: Total Loss | C21: =IF(G15="B",C19-C11-'Order Estimator'!C18,-C11+C19-'Order Estimator'!C18) -> -934.7006 | E21: Desirable Risk Reward | F21: 2 | I21: 10 | J21: =M20 -> 46735.03 | L21: =K21/J21 -> 0 | M21: =J21+K21 -> 46735.03
I22: 11 | J22: =M21 -> 46735.03 | L22: =K22/J22 -> 0 | M22: =J22+K22 -> 46735.03
I23: 12 | J23: =M22 -> 46735.03 | L23: =K23/J23 -> 0 | M23: =J23+K23 -> 46735.03
I24: 13 | J24: =M23 -> 46735.03 | L24: =K24/J24 -> 0 | M24: =J24+K24 -> 46735.03
I25: 14 | J25: =M24 -> 46735.03 | L25: =K25/J25 -> 0 | M25: =J25+K25 -> 46735.03
I26: 15 | J26: =M25 -> 46735.03 | L26: =K26/J26 -> 0 | M26: =J26+K26 -> 46735.03
I27: 16 | J27: =M26 -> 46735.03 | L27: =K27/J27 -> 0 | M27: =J27+K27 -> 46735.03
I28: 17 | J28: =M27 -> 46735.03 | L28: =K28/J28 -> 0 | M28: =J28+K28 -> 46735.03
I29: 18 | J29: =M28 -> 46735.03 | L29: =K29/J29 -> 0 | M29: =J29+K29 -> 46735.03
I30: 19 | J30: =M29 -> 46735.03 | L30: =K30/J30 -> 0 | M30: =J30+K30 -> 46735.03
I31: 20 | J31: =M30 -> 46735.03 | L31: =K31/J31 -> 0 | M31: =J31+K31 -> 46735.03
I32: 21 | J32: =M31 -> 46735.03 | L32: =K32/J32 -> 0 | M32: =J32+K32 -> 46735.03
I33: 22 | J33: =M32 -> 46735.03 | K33: 0 | L33: =K33/J33 -> 0 | M33: =J33+K33 -> 46735.03
I34: 23 | J34: =M33 -> 46735.03 | K34: 0 | L34: =K34/J34 -> 0 | M34: =J34+K34 -> 46735.03
I35: 24 | J35: =M34 -> 46735.03 | K35: 0 | L35: =K35/J35 -> 0 | M35: =J35+K35 -> 46735.03
I36: 25 | J36: =M35 -> 46735.03 | K36: 0 | L36: =K36/J36 -> 0 | M36: =J36+K36 -> 46735.03

Sheet Order Estimator
B2: Transaction Overview | E2: BUY ESTIMATION | H2: SELL ESTIMATION TGT HIT
B3: Quantity | C3: ='Intraday or Delivery RM'!C16 -> 349 | E3: Transactions Estimates # | H3: Transactions Estimates #
B4: Buy Price (Market) | C4: ='Intraday or Delivery RM'!C15 -> 600 | E4: Exchange Turnover | F4: =C5 -> 209400 | H4: Exchange Turnover | I4: ='Intraday or Delivery RM'!G12*'Order Estimator'!C3 -> 211390.52
B5: Trade Value | C5: =C4*C3 -> 209400 | E5: Brokerage (Buy) | F5: =IF('Intraday or Delivery RM'!$F$3="Intraday",IF(ROUND(($C$5*0.03)/100,2)>20,20,ROUND(($C$5*0.03)/100,2)),0) -> 20 | H5: Brokerage (Sell) | I5: =IF('Intraday or Delivery RM'!$F$3="Intraday",IF(ROUND(($C$5*0.03)/100,2)>20,20,ROUND(($C$5*0.03)/100,2)),0) -> 20
B6: Order Type | C6: Intraday | E6: Exchange Charges | F6: =F4*0.00297/100 -> 6.21918 | H6: Exchange Charges | I6: =I4*0.00297/100 -> 6.2782984
B7: Segment / Exchange | C7: Equity/NSE | E7: Securities Transaction Charges STT | F7: =IF('Intraday or Delivery RM'!$F$3="Intraday",0,ROUND(F4*0.1/100,2)) -> 0 | H7: Securities Transaction Charges STT | I7: =IF('Intraday or Delivery RM'!$F$3="Intraday",ROUND(I4*0.025/100,2),ROUND(I4*0.1/100,2)) -> 52.85
E8: Goods and Services Tax GST | F8: =(F5+F6)*0.18 -> 4.7194524 | H8: Goods and Services Tax GST | I8: =(I5+I6)*0.18 -> 4.7300937
E9: SEBI Charges | F9: =F4*0.0001/100 -> 0.2094 | H9: SEBI Charges | I9: =I4*0.0001/100 -> 0.21139052
E10: Investor Protection Fund Trust IPFT | F10: =F4*0.0001/100 -> 0.2094 | H10: Investor Protection Fund Trust IPFT | I10: =ROUND(I4*0.0001/100,2) -> 0.21
E11: Clearing Charges | F11: 0 | H11: Clearing Charges | I11: 0
E12: Stamp Duty | F12: =IF('Intraday or Delivery RM'!F3="Intraday",ROUND(F4*0.003/100,2),ROUND(F4*0.015/100,2)) -> 6.28 | H12: Stamp Duty | I12: 0
E13: DP Charges | F13: 0 | H13: DP Charges | I13: =IF('Intraday or Delivery RM'!$F$3="Intraday",0,12.5*(1+18%)) -> 0
E14: Total Tax & Charges (on buy) | F14: =SUM(F5:F13) -> 37.637432 | H14: Total Tax & Charges (on sell) | I14: =SUM(I5:I13) -> 84.279783
B16: TOTAL TAX & CHARGES
B17: On TGT HIT | C17: =F14+I14 -> 121.91721 | H17: SELL ESTIMATION SL HIT
B18: On SL HIT | C18: =F14+I29 -> 121.11614 | H18: Transactions Estimates #
H19: Exchange Turnover | I19: =C3*'Intraday or Delivery RM'!G13 -> 208586.42
H20: Brokerage (Sell) | I20: =IF('Intraday or Delivery RM'!$F$3="Intraday",IF(ROUND(($C$5*0.03)/100,2)>20,20,ROUND(($C$5*0.03)/100,2)),0) -> 20
H21: Exchange Charges | I21: =I19*0.00297/100 -> 6.1950165
H22: Securities Transaction Charges STT | I22: =IF('Intraday or Delivery RM'!$F$3="Intraday",ROUND(I19*0.025/100,2),ROUND(I19*0.1/100,2)) -> 52.15
H23: Goods and Services Tax GST | I23: =(I20+I21)*0.18 -> 4.715103
H24: SEBI Charges | I24: =I19*0.0001/100 -> 0.20858642
H25: Investor Protection Fund Trust IPFT | I25: =ROUND(I19*0.0001/100,2) -> 0.21
H26: Clearing Charges | I26: 0
H27: Stamp Duty | I27: 0
H28: DP Charges | I28: =IF('Intraday or Delivery RM'!$F$3="Intraday",0,12.5*(1+18%)) -> 0
H29: Total Tax & Charges (on sell) | I29: =SUM(I20:I28) -> 83.478706
